README.md
setup.cfg
setup.py
Logen/__init__.py
Logen/main.py
Logen/main_subcommand_convert.py
Logen/main_subcommand_list.py
Logen.egg-info/PKG-INFO
Logen.egg-info/SOURCES.txt
Logen.egg-info/dependency_links.txt
Logen.egg-info/entry_points.txt
Logen.egg-info/top_level.txt
Logen/converter/AndroidConverter.py
Logen/converter/ConverterInterface.py
Logen/converter/JSONConverter.py
Logen/converter/__init__.py
Logen/converter/iOSConverter.py
Logen/converter/iOSEnumConverter.py
Logen/lib/FileHelper.py
Logen/lib/JsonHelper.py
Logen/lib/TerminalStyle.py
Logen/lib/__init__.py
Logen/model/IntermediateEntry.py
Logen/model/IntermediateLanguage.py
Logen/model/IntermediateLocalization.py
Logen/model/LocalizationFile.py
Logen/model/MergeResult.py
Logen/model/__init__.py
Logen/tests/ConverterSpy.py
Logen/tests/TestHelper.py
Logen/tests/__init__.py
Logen/tests/run_all.py
Logen/tests/tests_AndroidConverter.py
Logen/tests/tests_ConverterBase.py
Logen/tests/tests_JSONConverter.py
Logen/tests/tests_bigtests.py
Logen/tests/tests_iOSConverter.py
Logen/tests/tests_iOSEnumConverter.py
Logen/tests/tests_main.py
Logen/tests/tests_subcommand_convert.py